[{"id":"FR53","name":"Poitou-Charentes","value":24.44},{"id":"FR52","name":"Bretagne","value":10.12},{"id":"UKK2","name":"Dorset and Somerset","value":26.91},{"id":"BG32","name":"Severen tsentralen","value":28.27},{"id":"LT00","name":"Lietuva","value":19.04},{"id":"FR71","name":"Rhône-Alpes","value":36.93},{"id":"CY00","name":"Kýpros","value":14.36},{"id":"EE00","name":"Eesti","value":15.38},{"id":"UKI2","name":"Outer London","value":12.54},{"id":"FR10","name":"Île de France","value":16.48},{"id":"EL54","name":"Thessalia","value":12.87},{"id":"ITF1","name":"Abruzzo","value":29.02},{"id":"HR03","name":"Jadranska Hrvatska","value":8.38},{"id":"PL51","name":"Dolnośląskie","value":16.29},{"id":"DE91","name":"Braunschweig","value":13.69},{"id":"BE25","name":"Prov. West-Vlaanderen","value":42.64},{"id":"FI1D","name":"Pohjois- ja Itä-Suomi","value":10.85},{"id":"BE23","name":"Prov. Oost-Vlaanderen","value":53.94},{"id":"PL61","name":"Kujawsko-Pomorskie","value":17.55},{"id":"PL63","name":"Pomorskie","value":16.16},{"id":"CZ03","name":"Jihozápad","value":16.09},{"id":"RO11","name":"Nord-Vest","value":12.86},{"id":"NL22","name":"Gelderland","value":48.65},{"id":"FR24","name":"Centre","value":31.01},{"id":"PT11","name":"Norte","value":44.33},{"id":"FR63","name":"Limousin","value":19.33},{"id":"DE40","name":"Brandenburg","value":20.67},{"id":"CH01","name":"Région lémanique","value":17.59},{"id":"UKJ2","name":"Surrey, East and West Sussex","value":12.65},{"id":"DE11","name":"Stuttgart","value":11.97},{"id":"DK01","name":"Hovedstaden","value":18.74},{"id":"DEB1","name":"Koblenz","value":38.84},{"id":"HU23","name":"Dél-Dunántúl","value":7.47},{"id":"DEG0","name":"Thüringen","value":18.36},{"id":"FR26","name":"Bourgogne","value":40.53},{"id":"ES52","name":"Comunidad Valenciana","value":49.69},{"id":"PL11","name":"Łódzkie","value":20.01},{"id":"PL21","name":"Małopolskie","value":28.94},{"id":"ES42","name":"Castilla-La Mancha","value":19.57},{"id":"CH04","name":"Zürich","value":42.53},{"id":"UKE1","name":"East Yorkshire and Northern Lincolnshire","value":15.78},{"id":"DED4","name":"Chemnitz","value":21.84},{"id":"BE34","name":"Prov. Luxembourg (BE)","value":36.61},{"id":"EL61","name":"Ipeiros","value":2.52},{"id":"ITC2","name":"Valle d'Aosta/Vallée d'Aoste","value":2.58},{"id":"PL62","name":"Warmińsko-Mazurskie","value":21.16},{"id":"BG42","name":"Yuzhen tsentralen","value":10.74},{"id":"PL31","name":"Lubelskie","value":15.46},{"id":"ES53","name":"Illes Balears","value":9.72},{"id":"ITC3","name":"Liguria","value":12.89},{"id":"ES51","name":"Cataluña","value":22.7},{"id":"BG31","name":"Severozapaden","value":15.86},{"id":"AT21","name":"Kärnten","value":17.22},{"id":"NL33","name":"Zuid-Holland","value":21.28},{"id":"DE27","name":"Schwaben","value":20.14},{"id":"ITH1","name":"Provincia Autonoma di Bolzano/Bozen","value":19.43},{"id":"FR42","name":"Alsace","value":30.45},{"id":"UKC1","name":"Tees Valley and Durham","value":37.66},{"id":"PL34","name":"Podlaskie","value":22.65},{"id":"ES30","name":"Comunidad de Madrid","value":19.55},{"id":"UKJ4","name":"Kent","value":22.55},{"id":"PT15","name":"Algarve","value":5.96},{"id":"ITI4","name":"Lazio","value":24.02},{"id":"DEA4","name":"Detmold","value":33.64},{"id":"FR83","name":"Corse","value":5.41},{"id":"ES41","name":"Castilla y León","value":36.63},{"id":"PL22","name":"Śląskie","value":26.31},{"id":"FR82","name":"Provence-Alpes-Côte d'Azur","value":15.92},{"id":"BG33","name":"Severoiztochen","value":6.4},{"id":"DED2","name":"Dresden","value":29.09},{"id":"FR30","name":"Nord - Pas-de-Calais","value":40.96},{"id":"ES64","name":"Ciudad Autónoma de Melilla","value":0.02},{"id":"RO31","name":"Sud - Muntenia","value":7.44},{"id":"DE71","name":"Darmstadt","value":27.69},{"id":"ITG1","name":"Sicilia","value":14.04},{"id":"UKE3","name":"South Yorkshire","value":21.53},{"id":"PT20","name":"Região Autónoma dos Açores","value":14.18},{"id":"EL65","name":"Peloponnisos","value":3.76},{"id":"RO32","name":"Bucureşti - Ilfov","value":13.11},{"id":"SI03","name":"Zahodna Slovenija","value":16.96},{"id":"IS02","name":"Landsbyggð","value":12.07},{"id":"HU22","name":"Nyugat-Dunántúl","value":10.4},{"id":"NL12","name":"Friesland (NL)","value":37.2},{"id":"EL30","name":"Attiki","value":17.46},{"id":"DED5","name":"Leipzig","value":26.4},{"id":"UKH2","name":"Bedfordshire and Hertfordshire","value":14.79},{"id":"UKL2","name":"East Wales","value":5.52},{"id":"UKE4","name":"West Yorkshire","value":24.85},{"id":"FR21","name":"Champagne-Ardenne","value":32.03},{"id":"ITF6","name":"Calabria","value":13.34},{"id":"CH07","name":"Ticino","value":19.54},{"id":"ITF2","name":"Molise","value":20.88},{"id":"UKG2","name":"Shropshire and Staffordshire","value":25.35},{"id":"NO07","name":"Nord-Norge","value":13.35},{"id":"NL11","name":"Groningen","value":24.67},{"id":"NL41","name":"Noord-Brabant","value":9.05},{"id":"SE22","name":"Sydsverige","value":13.25},{"id":"DE25","name":"Mittelfranken","value":13.06},{"id":"DE93","name":"Lüneburg","value":41.04},{"id":"CZ08","name":"Moravskoslezsko","value":17.37},{"id":"CZ02","name":"Střední Čechy","value":23.11},{"id":"EL64","name":"Sterea Ellada","value":18.81},{"id":"AT22","name":"Steiermark","value":18.39},{"id":"CZ06","name":"Jihovýchod","value":23.98},{"id":"DK05","name":"Nordjylland","value":6.41},{"id":"BE24","name":"Prov. Vlaams-Brabant","value":52.82},{"id":"FR72","name":"Auvergne","value":39.34},{"id":"FR22","name":"Picardie","value":42.04},{"id":"SE33","name":"Övre Norrland","value":7.2},{"id":"EL51","name":"Anatoliki Makedonia, Thraki","value":2.68},{"id":"UKD3","name":"Greater Manchester","value":34.89},{"id":"PT18","name":"Alentejo","value":13.37},{"id":"SK01","name":"Bratislavský kraj","value":15.58},{"id":"EL53","name":"Dytiki Makedonia","value":1.82},{"id":"IE02","name":"Southern and Eastern","value":16.7},{"id":"UKF2","name":"Leicestershire, Rutland and Northamptonshire","value":18.33},{"id":"ES22","name":"Comunidad Foral de Navarra","value":20.22},{"id":"UKJ3","name":"Hampshire and Isle of Wight","value":14.1},{"id":"CH03","name":"Nordwestschweiz","value":18.99},{"id":"BE22","name":"Prov. Limburg (BE)","value":47.89},{"id":"FR61","name":"Aquitaine","value":36.39},{"id":"UKG3","name":"West Midlands","value":14.36},{"id":"BG41","name":"Yugozapaden","value":15.23},{"id":"DK04","name":"Midtjylland","value":9.78},{"id":"SE31","name":"Norra Mellansverige","value":33.43},{"id":"PL33","name":"Świętokrzyskie","value":24.72},{"id":"NO05","name":"Vestlandet","value":11.45},{"id":"LU00","name":"Luxembourg","value":40.74},{"id":"FI1B","name":"Helsinki-Uusimaa","value":19.77},{"id":"FR25","name":"Basse-Normandie","value":26.42},{"id":"DEA1","name":"Düsseldorf","value":46.21},{"id":"ES21","name":"País Vasco","value":25.62},{"id":"DEE0","name":"Sachsen-Anhalt","value":29.14},{"id":"EL41","name":"Voreio Aigaio","value":0.36},{"id":"EL63","name":"Dytiki Ellada","value":21.28},{"id":"CZ04","name":"Severozápad","value":27.65},{"id":"UKD4","name":"Lancashire","value":43.05},{"id":"UKL1","name":"West Wales and The Valleys","value":31.56},{"id":"UKN0","name":"Northern Ireland","value":14.45},{"id":"AT33","name":"Tirol","value":23.48},{"id":"ITF5","name":"Basilicata","value":18.19},{"id":"NO01","name":"Oslo og Akershus","value":16.34},{"id":"UKD6","name":"Cheshire","value":29.66},{"id":"ES23","name":"La Rioja","value":33.95},{"id":"CZ07","name":"Střední Morava","value":30.85},{"id":"BE31","name":"Prov. Brabant Wallon","value":38.25},{"id":"DEF0","name":"Schleswig-Holstein","value":26.64},{"id":"HU21","name":"Közép-Dunántúl","value":10.65},{"id":"DEC0","name":"Saarland","value":43.22},{"id":"UKM3","name":"South Western Scotland","value":14.64},{"id":"UKD7","name":"Merseyside","value":31.79},{"id":"DE92","name":"Hannover","value":36.41},{"id":"DEA5","name":"Arnsberg","value":35.13},{"id":"ES11","name":"Galicia","value":30.03},{"id":"RO22","name":"Sud-Est","value":3.14},{"id":"HR04","name":"Kontinentalna Hrvatska","value":11.44},{"id":"ES12","name":"Principado de Asturias","value":30.46},{"id":"ITH2","name":"Provincia Autonoma di Trento","value":27.67},{"id":"SE23","name":"Västsverige","value":23.4},{"id":"ES61","name":"Andalucía","value":16.72},{"id":"AT31","name":"Oberösterreich","value":44.35},{"id":"ITI2","name":"Umbria","value":18.13},{"id":"NO03","name":"Sør-Østlandet","value":34.38},{"id":"FR43","name":"Franche-Comté","value":22.43},{"id":"NO06","name":"Trøndelag","value":8.59},{"id":"CH06","name":"Zentralschweiz","value":39.45},{"id":"ES24","name":"Aragón","value":24.24},{"id":"HU33","name":"Dél-Alföld","value":14.67},{"id":"DE94","name":"Weser-Ems","value":20.46},{"id":"FR81","name":"Languedoc-Roussillon","value":23.38},{"id":"FI1C","name":"Etelä-Suomi","value":38.42},{"id":"BE10","name":"Région de Bruxelles-Capitale / Brussels Hoofdstedelijk Gewest","value":29.11},{"id":"AT13","name":"Wien","value":20.71},{"id":"NL21","name":"Overijssel","value":44.99},{"id":"ITH4","name":"Friuli-Venezia Giulia","value":29.32},{"id":"DEA3","name":"Münster","value":49.73},{"id":"SE21","name":"Småland med öarna","value":28.16},{"id":"NL32","name":"Noord-Holland","value":40.36},{"id":"ITF4","name":"Puglia","value":38.87},{"id":"FRY1","name":"Guadeloupe","value":12.86},{"id":"PL52","name":"Opolskie","value":10.94},{"id":"FI19","name":"Länsi-Suomi","value":13.85},{"id":"ES62","name":"Región de Murcia","value":24.24},{"id":"DEA2","name":"Köln","value":48.78},{"id":"SK04","name":"Východné Slovensko","value":24.5},{"id":"UKC2","name":"Northumberland and Tyne and Wear","value":30.78},{"id":"AT12","name":"Niederösterreich","value":36.6},{"id":"SE12","name":"Östra Mellansverige","value":10.83},{"id":"BE35","name":"Prov. Namur","value":32.69},{"id":"ITC4","name":"Lombardia","value":52},{"id":"RO41","name":"Sud-Vest Oltenia","value":2.57},{"id":"ITG2","name":"Sardegna","value":13.74},{"id":"NO04","name":"Agder og Rogaland","value":10.61},{"id":"ITH5","name":"Emilia-Romagna","value":40.94},{"id":"AT34","name":"Vorarlberg","value":14.62},{"id":"DEB2","name":"Trier","value":29.96},{"id":"ES43","name":"Extremadura","value":12.37},{"id":"FR62","name":"Midi-Pyrénées","value":18.55},{"id":"DE23","name":"Oberpfalz","value":12.84},{"id":"NL31","name":"Utrecht","value":23.96},{"id":"HU32","name":"Észak-Alföld","value":27.01},{"id":"ES70","name":"Canarias","value":13.14},{"id":"PL12","name":"Mazowieckie","value":32.68},{"id":"BG34","name":"Yugoiztochen","value":22.36},{"id":"UKJ1","name":"Berkshire, Buckinghamshire and Oxfordshire","value":15.34},{"id":"ITI3","name":"Marche","value":39.01},{"id":"NL34","name":"Zeeland","value":37.3},{"id":"PL32","name":"Podkarpackie","value":17.61},{"id":"SE32","name":"Mellersta Norrland","value":16.78},{"id":"DE13","name":"Freiburg","value":18.27},{"id":"AT32","name":"Salzburg","value":28.65},{"id":"ITF3","name":"Campania","value":25.11},{"id":"RO42","name":"Vest","value":7.93},{"id":"CZ01","name":"Praha","value":15.64},{"id":"UKM6","name":"Highlands and Islands","value":17.15},{"id":"DE80","name":"Mecklenburg-Vorpommern","value":39.89},{"id":"FRY2","name":"Martinique","value":1.5},{"id":"UKK4","name":"Devon","value":16.49},{"id":"FI20","name":"Åland","value":6.32},{"id":"UKK1","name":"Gloucestershire, Wiltshire and Bristol/Bath area","value":14.37},{"id":"LV00","name":"Latvija","value":29.48},{"id":"RO12","name":"Centru","value":5.35},{"id":"SK02","name":"Západné Slovensko","value":21.88},{"id":"IS01","name":"Höfuðborgarsvæði","value":9.62},{"id":"UKH3","name":"Essex","value":16.58},{"id":"EL43","name":"Kriti","value":20.95},{"id":"DE22","name":"Niederbayern","value":20.87},{"id":"BE21","name":"Prov. Antwerpen","value":41.44},{"id":"FR51","name":"Pays de la Loire","value":35.78},{"id":"PL41","name":"Wielkopolskie","value":15.73},{"id":"NL42","name":"Limburg (NL)","value":45.82},{"id":"IE01","name":"Border, Midland and Western","value":11.09},{"id":"FRY3","name":"Guyane","value":2.03},{"id":"ES13","name":"Cantabria","value":7.27},{"id":"EL52","name":"Kentriki Makedonia","value":21.34},{"id":"DE60","name":"Hamburg","value":36.4},{"id":"UKF3","name":"Lincolnshire","value":19.36},{"id":"DK02","name":"Sjælland","value":33.31},{"id":"DE26","name":"Unterfranken","value":36.01},{"id":"SK03","name":"Stredné Slovensko","value":22.16},{"id":"CH02","name":"Espace Mittelland","value":30.27},{"id":"RO21","name":"Nord-Est","value":20.82},{"id":"NO02","name":"Hedmark og Oppland","value":13.63},{"id":"NL13","name":"Drenthe","value":35.93},{"id":"UKE2","name":"North Yorkshire","value":23.33},{"id":"BE32","name":"Prov. Hainaut","value":40.59},{"id":"DE21","name":"Oberbayern","value":10.41},{"id":"UKM2","name":"Eastern Scotland","value":12.33},{"id":"CH05","name":"Ostschweiz","value":29},{"id":"DE72","name":"Gießen","value":31.36},{"id":"PT30","name":"Região Autónoma da Madeira","value":3.2},{"id":"AT11","name":"Burgenland (AT)","value":21.58},{"id":"NL23","name":"Flevoland","value":39.59},{"id":"DE24","name":"Oberfranken","value":20.66},{"id":"BE33","name":"Prov. Liège","value":38.76},{"id":"UKD1","name":"Cumbria","value":30.09},{"id":"PL42","name":"Zachodniopomorskie","value":23.16},{"id":"FR41","name":"Lorraine","value":41.42},{"id":"EL42","name":"Notio Aigaio","value":1.58},{"id":"DK03","name":"Syddanmark","value":25.96},{"id":"DE73","name":"Kassel","value":29.99},{"id":"EL62","name":"Ionia Nisia","value":1.23},{"id":"PL43","name":"Lubuskie","value":20.17},{"id":"ITC1","name":"Piemonte","value":41.93},{"id":"ITI1","name":"Toscana","value":18.68},{"id":"MT00","name":"Malta","value":7.95},{"id":"SE11","name":"Stockholm","value":4.89},{"id":"UKK3","name":"Cornwall and Isles of Scilly","value":30.93},{"id":"UKF1","name":"Derbyshire and Nottinghamshire","value":34.16},{"id":"UKI1","name":"Inner London","value":7.23},{"id":"DE14","name":"Tübingen","value":13.71},{"id":"PT17","name":"Lisboa","value":23.19},{"id":"DEB3","name":"Rheinhessen-Pfalz","value":40.54},{"id":"UKG1","name":"Herefordshire, Worcestershire and Warwickshire","value":31.81},{"id":"FR23","name":"Haute-Normandie","value":38.38},{"id":"DE50","name":"Bremen","value":17.79},{"id":"DE30","name":"Berlin","value":14.64},{"id":"FRY4","name":"Réunion","value":8.39},{"id":"PT16","name":"Centro (PT)","value":36.65},{"id":"LI00","name":"Liechtenstein","value":20.7},{"id":"UKH1","name":"East Anglia","value":13.79},{"id":"DE12","name":"Karlsruhe","value":12.07},{"id":"CZ05","name":"Severovýchod","value":29.44},{"id":"HU31","name":"Észak-Magyarország","value":11.66},{"id":"ITH3","name":"Veneto","value":36.27},{"id":"HU10","name":"Közép-Magyarország","value":12.33},{"id":"UKM5","name":"North Eastern Scotland","value":9.98}]
