[{"id":"DE50","name":"Bremen","value":71.9523,"binary":0,"link.rca":0,"RD.added":26.8628},{"id":"SE11","name":"Stockholm","value":66.4528,"binary":0,"link.rca":0,"RD.added":19.9566},{"id":"UKH1","name":"East Anglia","value":56.187,"binary":1,"link.rca":1.16,"RD.added":42.3595},{"id":"BE24","name":"Prov. Vlaams-Brabant","value":89.5509,"binary":0,"link.rca":0,"RD.added":41.9877},{"id":"BE10","name":"Région de Bruxelles-Capitale / Brussels Hoofdstedelijk Gewest","value":60.7699,"binary":0,"link.rca":0,"RD.added":16.0631},{"id":"SI03","name":"Zahodna Slovenija","value":58.5701,"binary":0,"link.rca":0,"RD.added":15.247},{"id":"UKI2","name":"Outer London","value":98.3501,"binary":0,"link.rca":0,"RD.added":54.1768},{"id":"UKD7","name":"Merseyside","value":49.9542,"binary":0,"link.rca":0,"RD.added":11.5368},{"id":"ITC1","name":"Piemonte","value":48.8543,"binary":0,"link.rca":0,"RD.added":11.1927},{"id":"ITH1","name":"Provincia Autonoma di Bolzano/Bozen","value":61.5949,"binary":0,"link.rca":0,"RD.added":16.804},{"id":"ES42","name":"Castilla-La Mancha","value":56.6453,"binary":0,"link.rca":0,"RD.added":14.3018},{"id":"DK05","name":"Nordjylland","value":33.1806,"binary":0,"link.rca":0,"RD.added":4.5411},{"id":"UKM5","name":"North Eastern Scotland","value":39.78,"binary":0,"link.rca":0,"RD.added":8.0245},{"id":"SE23","name":"Västsverige","value":49.6792,"binary":0,"link.rca":0,"RD.added":11.4933},{"id":"DE26","name":"Unterfranken","value":57.1952,"binary":0,"link.rca":0,"RD.added":14.3205},{"id":"EL63","name":"Dytiki Ellada","value":52.429,"binary":0,"link.rca":0,"RD.added":12.4804},{"id":"HU32","name":"Észak-Alföld","value":68.9276,"binary":0,"link.rca":0,"RD.added":22.8865},{"id":"CZ05","name":"Severovýchod","value":79.3767,"binary":0,"link.rca":0,"RD.added":32.1949},{"id":"DE60","name":"Hamburg","value":48.3043,"binary":0,"link.rca":0,"RD.added":11.0362},{"id":"ES13","name":"Cantabria","value":71.4024,"binary":0,"link.rca":0,"RD.added":26.4618},{"id":"CH03","name":"Nordwestschweiz","value":93.1256,"binary":0,"link.rca":0,"RD.added":44.9691},{"id":"UKM3","name":"South Western Scotland","value":84.6013,"binary":0,"link.rca":0,"RD.added":36.0834},{"id":"RO21","name":"Nord-Est","value":78.0018,"binary":0,"link.rca":0,"RD.added":31.0176},{"id":"UKD3","name":"Greater Manchester","value":56.9203,"binary":0,"link.rca":0,"RD.added":14.318},{"id":"HU21","name":"Közép-Dunántúl","value":47.7544,"binary":0,"link.rca":0,"RD.added":11.0034},{"id":"NL34","name":"Zeeland","value":30.9808,"binary":0,"link.rca":0,"RD.added":3.271},{"id":"DE91","name":"Braunschweig","value":59.3951,"binary":0,"link.rca":0,"RD.added":15.4934},{"id":"FR42","name":"Alsace","value":48.5793,"binary":0,"link.rca":0,"RD.added":11.1778},{"id":"FI19","name":"Länsi-Suomi","value":66.7278,"binary":0,"link.rca":0,"RD.added":20.249},{"id":"ITC4","name":"Lombardia","value":61.8698,"binary":0,"link.rca":0,"RD.added":16.8597},{"id":"UKG2","name":"Shropshire and Staffordshire","value":52.7039,"binary":0,"link.rca":0,"RD.added":12.4941},{"id":"DE14","name":"Tübingen","value":76.9019,"binary":0,"link.rca":0,"RD.added":30.1335},{"id":"FR26","name":"Bourgogne","value":65.3529,"binary":0,"link.rca":0,"RD.added":18.8735},{"id":"PL22","name":"Śląskie","value":75.527,"binary":0,"link.rca":0,"RD.added":29.2703},{"id":"EL54","name":"Thessalia","value":77.7269,"binary":0,"link.rca":0,"RD.added":31.0016},{"id":"UKK4","name":"Devon","value":67.0027,"binary":0,"link.rca":0,"RD.added":20.4262},{"id":"SE33","name":"Övre Norrland","value":43.0797,"binary":0,"link.rca":0,"RD.added":9.2921},{"id":"ITF1","name":"Abruzzo","value":46.1045,"binary":0,"link.rca":0,"RD.added":10.6211},{"id":"DEA4","name":"Detmold","value":34.2805,"binary":0,"link.rca":0,"RD.added":5.633},{"id":"FR71","name":"Rhône-Alpes","value":68.6526,"binary":0,"link.rca":0,"RD.added":22.7391},{"id":"UKM2","name":"Eastern Scotland","value":98.6251,"binary":0,"link.rca":0,"RD.added":55.3727},{"id":"CH07","name":"Ticino","value":89.8258,"binary":0,"link.rca":0,"RD.added":42.2135},{"id":"EL30","name":"Attiki","value":54.5371,"binary":0,"link.rca":0,"RD.added":13.5018},{"id":"IE01","name":"Border, Midland and Western","value":86.8011,"binary":0,"link.rca":0,"RD.added":39.6156},{"id":"ITI1","name":"Toscana","value":82.9514,"binary":0,"link.rca":0,"RD.added":35.3296},{"id":"FR61","name":"Aquitaine","value":49.4042,"binary":0,"link.rca":0,"RD.added":11.3281},{"id":"ITF4","name":"Puglia","value":75.2521,"binary":0,"link.rca":0,"RD.added":29.1026},{"id":"DE80","name":"Mecklenburg-Vorpommern","value":82.6764,"binary":0,"link.rca":0,"RD.added":35.2644},{"id":"FR63","name":"Limousin","value":79.1017,"binary":0,"link.rca":0,"RD.added":32.1311},{"id":"DEB2","name":"Trier","value":38.9551,"binary":0,"link.rca":0,"RD.added":7.8439},{"id":"DEF0","name":"Schleswig-Holstein","value":83.7764,"binary":0,"link.rca":0,"RD.added":35.5359},{"id":"MT00","name":"Malta","value":70.0275,"binary":0,"link.rca":0,"RD.added":23.9002},{"id":"IS01","name":"Höfuðborgarsvæði","value":76.6269,"binary":0,"link.rca":0,"RD.added":30.1064},{"id":"LU00","name":"Luxembourg","value":55.2704,"binary":0,"link.rca":0,"RD.added":13.5788},{"id":"FR53","name":"Poitou-Charentes","value":69.2026,"binary":0,"link.rca":0,"RD.added":23.3963},{"id":"DK04","name":"Midtjylland","value":32.3556,"binary":0,"link.rca":0,"RD.added":4.2585},{"id":"PL51","name":"Dolnośląskie","value":41.9798,"binary":0,"link.rca":0,"RD.added":8.5082},{"id":"CZ07","name":"Střední Morava","value":54.0788,"binary":0,"link.rca":0,"RD.added":13.2504},{"id":"PL41","name":"Wielkopolskie","value":91.7507,"binary":0,"link.rca":0,"RD.added":44.0663},{"id":"DE12","name":"Karlsruhe","value":62.9698,"binary":0,"link.rca":0,"RD.added":17.5454},{"id":"DE30","name":"Berlin","value":98.9001,"binary":0,"link.rca":0,"RD.added":56.1378},{"id":"DE73","name":"Kassel","value":68.1027,"binary":0,"link.rca":0,"RD.added":21.9022},{"id":"ITF2","name":"Molise","value":51.3291,"binary":0,"link.rca":0,"RD.added":11.7435},{"id":"CZ03","name":"Jihozápad","value":73.0522,"binary":0,"link.rca":0,"RD.added":27.5123},{"id":"SK02","name":"Západné Slovensko","value":64.3446,"binary":0,"link.rca":0,"RD.added":18.2207},{"id":"FR52","name":"Bretagne","value":94.5005,"binary":0,"link.rca":0,"RD.added":46.3949},{"id":"ITH4","name":"Friuli-Venezia Giulia","value":43.6297,"binary":0,"link.rca":0,"RD.added":9.7362},{"id":"SE31","name":"Norra Mellansverige","value":37.0302,"binary":0,"link.rca":0,"RD.added":6.4577},{"id":"ITC3","name":"Liguria","value":95.0504,"binary":0,"link.rca":0,"RD.added":48.3348},{"id":"UKI1","name":"Inner London","value":94.7754,"binary":0,"link.rca":0,"RD.added":47.2402},{"id":"FR51","name":"Pays de la Loire","value":47.2044,"binary":0,"link.rca":0,"RD.added":10.8723},{"id":"UKJ3","name":"Hampshire and Isle of Wight","value":65.6279,"binary":0,"link.rca":0,"RD.added":19.2503},{"id":"UKJ1","name":"Berkshire, Buckinghamshire and Oxfordshire","value":96.7003,"binary":0,"link.rca":0,"RD.added":49.8548},{"id":"FR10","name":"Île de France","value":63.2447,"binary":0,"link.rca":0,"RD.added":17.737},{"id":"CH05","name":"Ostschweiz","value":83.2264,"binary":0,"link.rca":0,"RD.added":35.3823},{"id":"BE25","name":"Prov. West-Vlaanderen","value":37.8552,"binary":0,"link.rca":0,"RD.added":6.8205},{"id":"ITH2","name":"Provincia Autonoma di Trento","value":61.0449,"binary":0,"link.rca":0,"RD.added":16.4955},{"id":"ITC2","name":"Valle d'Aosta/Vallée d'Aoste","value":68.3776,"binary":0,"link.rca":0,"RD.added":22.6558},{"id":"UKL2","name":"East Wales","value":81.5765,"binary":0,"link.rca":0,"RD.added":33.3724},{"id":"LV00","name":"Latvija","value":44.1797,"binary":0,"link.rca":0,"RD.added":9.8632},{"id":"UKL1","name":"West Wales and The Valleys","value":86.2511,"binary":0,"link.rca":0,"RD.added":39.1691},{"id":"ITI3","name":"Marche","value":53.5289,"binary":0,"link.rca":0,"RD.added":13.0693},{"id":"DK03","name":"Syddanmark","value":33.7305,"binary":0,"link.rca":0,"RD.added":5.3436},{"id":"BE33","name":"Prov. Liège","value":50.7791,"binary":0,"link.rca":0,"RD.added":11.634},{"id":"UKJ4","name":"Kent","value":66.1778,"binary":0,"link.rca":0,"RD.added":19.6892},{"id":"DE23","name":"Oberpfalz","value":49.1292,"binary":0,"link.rca":0,"RD.added":11.3096},{"id":"UKF2","name":"Leicestershire, Rutland and Northamptonshire","value":58.8451,"binary":0,"link.rca":0,"RD.added":15.3236},{"id":"EL43","name":"Kriti","value":87.626,"binary":0,"link.rca":0,"RD.added":40.2744},{"id":"CH06","name":"Zentralschweiz","value":99.45,"binary":0,"link.rca":0,"RD.added":57.059},{"id":"PT16","name":"Centro (PT)","value":86.5261,"binary":0,"link.rca":0,"RD.added":39.3767},{"id":"BG41","name":"Yugozapaden","value":90.1008,"binary":0,"link.rca":0,"RD.added":42.2301},{"id":"FR30","name":"Nord - Pas-de-Calais","value":70.8524,"binary":0,"link.rca":0,"RD.added":25.9091},{"id":"AT12","name":"Niederösterreich","value":55.8203,"binary":0,"link.rca":0,"RD.added":13.7989},{"id":"NL41","name":"Noord-Brabant","value":66.0862,"binary":2,"link.rca":0.39,"RD.added":59.2877},{"id":"UKK2","name":"Dorset and Somerset","value":80.7516,"binary":0,"link.rca":0,"RD.added":33.1127},{"id":"UKN0","name":"Northern Ireland","value":81.8515,"binary":0,"link.rca":0,"RD.added":33.8645},{"id":"NO01","name":"Oslo og Akershus","value":87.901,"binary":0,"link.rca":0,"RD.added":40.393},{"id":"PL11","name":"Łódzkie","value":72.5023,"binary":0,"link.rca":0,"RD.added":26.9601},{"id":"RO42","name":"Vest","value":71.1274,"binary":0,"link.rca":0,"RD.added":25.9352},{"id":"UKE2","name":"North Yorkshire","value":74.9771,"binary":0,"link.rca":0,"RD.added":28.624},{"id":"UKD6","name":"Cheshire","value":71.6774,"binary":0,"link.rca":0,"RD.added":26.7822},{"id":"ES70","name":"Canarias","value":85.4262,"binary":0,"link.rca":0,"RD.added":38.3626},{"id":"RO12","name":"Centru","value":87.3511,"binary":0,"link.rca":0,"RD.added":39.7782},{"id":"NO03","name":"Sør-Østlandet","value":41.4299,"binary":0,"link.rca":0,"RD.added":8.3776},{"id":"EL52","name":"Kentriki Makedonia","value":67.2777,"binary":0,"link.rca":0,"RD.added":20.6297},{"id":"UKD4","name":"Lancashire","value":89.2759,"binary":0,"link.rca":0,"RD.added":41.8649},{"id":"DE21","name":"Oberbayern","value":65.0779,"binary":0,"link.rca":0,"RD.added":18.6341},{"id":"NL42","name":"Limburg (NL)","value":45.5545,"binary":3,"link.rca":0,"RD.added":10.5507},{"id":"ITH3","name":"Veneto","value":47.4794,"binary":0,"link.rca":0,"RD.added":10.9443},{"id":"DE25","name":"Mittelfranken","value":97.8002,"binary":0,"link.rca":0,"RD.added":51.4109},{"id":"DEB1","name":"Koblenz","value":62.6948,"binary":0,"link.rca":0,"RD.added":17.4679},{"id":"DE71","name":"Darmstadt","value":73.8772,"binary":0,"link.rca":0,"RD.added":28.3489},{"id":"UKH3","name":"Essex","value":61.3199,"binary":0,"link.rca":0,"RD.added":16.5495},{"id":"AT31","name":"Oberösterreich","value":35.6554,"binary":0,"link.rca":0,"RD.added":6.1267},{"id":"HU10","name":"Közép-Magyarország","value":77.4519,"binary":0,"link.rca":0,"RD.added":30.8949},{"id":"SI04","name":"Vzhodna Slovenija","value":83.5014,"binary":0,"link.rca":0,"RD.added":35.4349},{"id":"DEC0","name":"Saarland","value":93.4005,"binary":0,"link.rca":0,"RD.added":45.679},{"id":"UKM6","name":"Highlands and Islands","value":88.451,"binary":0,"link.rca":0,"RD.added":41.5551},{"id":"FR23","name":"Haute-Normandie","value":39.2301,"binary":0,"link.rca":0,"RD.added":7.8883},{"id":"UKG1","name":"Herefordshire, Worcestershire and Warwickshire","value":93.9505,"binary":0,"link.rca":0,"RD.added":46.093},{"id":"AT32","name":"Salzburg","value":73.6022,"binary":0,"link.rca":0,"RD.added":28.193},{"id":"HU33","name":"Dél-Alföld","value":40.33,"binary":0,"link.rca":0,"RD.added":8.0964},{"id":"DK02","name":"Sjælland","value":78.2768,"binary":0,"link.rca":0,"RD.added":31.4154},{"id":"CZ08","name":"Moravskoslezsko","value":51.604,"binary":0,"link.rca":0,"RD.added":12.3479},{"id":"FR81","name":"Languedoc-Roussillon","value":97.5252,"binary":0,"link.rca":0,"RD.added":50.8983},{"id":"DE40","name":"Brandenburg","value":84.8763,"binary":0,"link.rca":0,"RD.added":36.208},{"id":"ES21","name":"País Vasco","value":51.879,"binary":0,"link.rca":0,"RD.added":12.3748},{"id":"PL32","name":"Podkarpackie","value":34.8304,"binary":0,"link.rca":0,"RD.added":6.0056},{"id":"SE32","name":"Mellersta Norrland","value":36.4803,"binary":0,"link.rca":0,"RD.added":6.1876},{"id":"UKE3","name":"South Yorkshire","value":67.8277,"binary":0,"link.rca":0,"RD.added":21.2076},{"id":"DE27","name":"Schwaben","value":44.4546,"binary":0,"link.rca":0,"RD.added":9.9828},{"id":"FI1D","name":"Pohjois- ja Itä-Suomi","value":91.4757,"binary":1,"link.rca":0,"RD.added":44.0342},{"id":"CZ01","name":"Praha","value":85.9762,"binary":0,"link.rca":0,"RD.added":39.0954},{"id":"PL62","name":"Warmińsko-Mazurskie","value":65.9028,"binary":0,"link.rca":0,"RD.added":19.6829},{"id":"PL42","name":"Zachodniopomorskie","value":46.6544,"binary":0,"link.rca":0,"RD.added":10.8427},{"id":"UKK1","name":"Gloucestershire, Wiltshire and Bristol/Bath area","value":82.4015,"binary":0,"link.rca":0,"RD.added":35.2002},{"id":"DK01","name":"Hovedstaden","value":94.2255,"binary":0,"link.rca":0,"RD.added":46.1676},{"id":"FR22","name":"Picardie","value":36.2053,"binary":0,"link.rca":0,"RD.added":6.1799},{"id":"BE22","name":"Prov. Limburg (BE)","value":74.7021,"binary":0,"link.rca":0,"RD.added":28.5379},{"id":"PT15","name":"Algarve","value":69.4775,"binary":0,"link.rca":0,"RD.added":23.5945},{"id":"AT21","name":"Kärnten","value":56.0953,"binary":0,"link.rca":0,"RD.added":13.9197},{"id":"SE12","name":"Östra Mellansverige","value":59.67,"binary":0,"link.rca":0,"RD.added":15.7888},{"id":"PT17","name":"Lisboa","value":96.4253,"binary":0,"link.rca":0,"RD.added":49.7436},{"id":"DED5","name":"Leipzig","value":76.077,"binary":0,"link.rca":0,"RD.added":29.4225},{"id":"FRY2","name":"Martinique","value":80.2016,"binary":0,"link.rca":0,"RD.added":32.7432},{"id":"RO32","name":"Bucureşti - Ilfov","value":95.8753,"binary":0,"link.rca":0,"RD.added":49.2205},{"id":"ES61","name":"Andalucía","value":64.8029,"binary":0,"link.rca":0,"RD.added":18.2904},{"id":"FR62","name":"Midi-Pyrénées","value":35.9303,"binary":0,"link.rca":0,"RD.added":6.1318},{"id":"DED4","name":"Chemnitz","value":42.5298,"binary":0,"link.rca":0,"RD.added":9.0724},{"id":"PT11","name":"Norte","value":96.9753,"binary":0,"link.rca":0,"RD.added":49.8635},{"id":"PL12","name":"Mazowieckie","value":97.2502,"binary":0,"link.rca":0,"RD.added":49.9814},{"id":"BE23","name":"Prov. Oost-Vlaanderen","value":44.7296,"binary":1,"link.rca":0,"RD.added":10.0828},{"id":"NL11","name":"Groningen","value":92.0257,"binary":0,"link.rca":0,"RD.added":44.262},{"id":"UKF3","name":"Lincolnshire","value":74.1522,"binary":0,"link.rca":0,"RD.added":28.4318},{"id":"ITG1","name":"Sicilia","value":79.6517,"binary":0,"link.rca":0,"RD.added":32.2754},{"id":"NL21","name":"Overijssel","value":45.0046,"binary":1,"link.rca":0,"RD.added":10.2392},{"id":"DEB3","name":"Rheinhessen-Pfalz","value":35.1054,"binary":1,"link.rca":0,"RD.added":6.0471},{"id":"FR41","name":"Lorraine","value":39.505,"binary":0,"link.rca":0,"RD.added":7.9409},{"id":"ITH5","name":"Emilia-Romagna","value":42.8048,"binary":0,"link.rca":0,"RD.added":9.2237},{"id":"NL32","name":"Noord-Holland","value":54.7663,"binary":4,"link.rca":0,"RD.added":13.5026},{"id":"IE02","name":"Southern and Eastern","value":98.0752,"binary":0,"link.rca":0,"RD.added":52.8398},{"id":"IS02","name":"Landsbyggð","value":31.2557,"binary":0,"link.rca":0,"RD.added":3.5854},{"id":"ITI4","name":"Lazio","value":81.0266,"binary":0,"link.rca":0,"RD.added":33.1526},{"id":"BE32","name":"Prov. Hainaut","value":36.7553,"binary":0,"link.rca":0,"RD.added":6.4202},{"id":"ES22","name":"Comunidad Foral de Navarra","value":62.1448,"binary":0,"link.rca":0,"RD.added":17.2161},{"id":"FR82","name":"Provence-Alpes-Côte d'Azur","value":96.1503,"binary":0,"link.rca":0,"RD.added":49.4383},{"id":"BE35","name":"Prov. Namur","value":53.8038,"binary":0,"link.rca":0,"RD.added":13.1555},{"id":"RO31","name":"Sud - Muntenia","value":67.5527,"binary":0,"link.rca":0,"RD.added":21.1769},{"id":"ES30","name":"Comunidad de Madrid","value":59.1201,"binary":0,"link.rca":0,"RD.added":15.3942},{"id":"CZ06","name":"Jihovýchod","value":57.4702,"binary":0,"link.rca":0,"RD.added":14.6315},{"id":"DEA5","name":"Arnsberg","value":38.4051,"binary":0,"link.rca":0,"RD.added":7.1212},{"id":"CZ04","name":"Severozápad","value":38.6801,"binary":0,"link.rca":0,"RD.added":7.6492},{"id":"NL22","name":"Gelderland","value":41.1549,"binary":7,"link.rca":0,"RD.added":8.1425},{"id":"NO05","name":"Vestlandet","value":40.8799,"binary":0,"link.rca":0,"RD.added":8.1061},{"id":"ES24","name":"Aragón","value":40.6049,"binary":0,"link.rca":0,"RD.added":8.1007},{"id":"PL34","name":"Podlaskie","value":72.7773,"binary":0,"link.rca":0,"RD.added":26.981},{"id":"BE31","name":"Prov. Brabant Wallon","value":57.7452,"binary":0,"link.rca":0,"RD.added":14.6508},{"id":"BE21","name":"Prov. Antwerpen","value":69.7525,"binary":0,"link.rca":0,"RD.added":23.7792},{"id":"HU22","name":"Nyugat-Dunántúl","value":70.3025,"binary":0,"link.rca":0,"RD.added":24.5616},{"id":"DE22","name":"Niederbayern","value":50.5041,"binary":0,"link.rca":0,"RD.added":11.5718},{"id":"DE72","name":"Gießen","value":53.2539,"binary":0,"link.rca":0,"RD.added":13.014},{"id":"ES52","name":"Comunidad Valenciana","value":78.8268,"binary":1,"link.rca":0,"RD.added":31.8835},{"id":"RO11","name":"Nord-Vest","value":87.0761,"binary":0,"link.rca":0,"RD.added":39.6246},{"id":"DED2","name":"Dresden","value":63.7947,"binary":0,"link.rca":0,"RD.added":18.0011},{"id":"DE92","name":"Hannover","value":40.055,"binary":0,"link.rca":0,"RD.added":8.0874},{"id":"DEE0","name":"Sachsen-Anhalt","value":45.2796,"binary":0,"link.rca":0,"RD.added":10.5305},{"id":"AT11","name":"Burgenland (AT)","value":41.7049,"binary":0,"link.rca":0,"RD.added":8.3859},{"id":"NO04","name":"Agder og Rogaland","value":37.3052,"binary":0,"link.rca":0,"RD.added":6.6083},{"id":"HR04","name":"Kontinentalna Hrvatska","value":74.4271,"binary":0,"link.rca":0,"RD.added":28.4957},{"id":"SK03","name":"Stredné Slovensko","value":88.7259,"binary":0,"link.rca":0,"RD.added":41.6494},{"id":"PL31","name":"Lubelskie","value":89.0009,"binary":0,"link.rca":0,"RD.added":41.7689},{"id":"LT00","name":"Lietuva","value":93.6755,"binary":0,"link.rca":0,"RD.added":45.7916},{"id":"PL33","name":"Świętokrzyskie","value":34.5555,"binary":0,"link.rca":0,"RD.added":5.6701},{"id":"FR43","name":"Franche-Comté","value":58.0202,"binary":0,"link.rca":0,"RD.added":14.6639},{"id":"FI1C","name":"Etelä-Suomi","value":52.9789,"binary":1,"link.rca":0,"RD.added":12.9506},{"id":"FR21","name":"Champagne-Ardenne","value":76.352,"binary":0,"link.rca":0,"RD.added":29.8943},{"id":"UKH2","name":"Bedfordshire and Hertfordshire","value":64.0697,"binary":0,"link.rca":0,"RD.added":18.0957},{"id":"DEA2","name":"Köln","value":45.8295,"binary":0,"link.rca":0,"RD.added":10.5941},{"id":"BG33","name":"Severoiztochen","value":82.1265,"binary":0,"link.rca":0,"RD.added":34.2198},{"id":"AT34","name":"Vorarlberg","value":46.9294,"binary":0,"link.rca":0,"RD.added":10.8515},{"id":"UKJ2","name":"Surrey, East and West Sussex","value":79.9267,"binary":0,"link.rca":0,"RD.added":32.2805},{"id":"CZ02","name":"Střední Čechy","value":62.4198,"binary":0,"link.rca":0,"RD.added":17.4651},{"id":"UKF1","name":"Derbyshire and Nottinghamshire","value":31.5307,"binary":0,"link.rca":0,"RD.added":3.6772},{"id":"DE11","name":"Stuttgart","value":56.3703,"binary":0,"link.rca":0,"RD.added":14.1884},{"id":"ITI2","name":"Umbria","value":37.5802,"binary":0,"link.rca":0,"RD.added":6.8148},{"id":"FRY4","name":"Réunion","value":34.0055,"binary":0,"link.rca":0,"RD.added":5.5684},{"id":"EE00","name":"Eesti","value":92.5756,"binary":0,"link.rca":0,"RD.added":44.873},{"id":"ES62","name":"Región de Murcia","value":75.802,"binary":0,"link.rca":0,"RD.added":29.3396},{"id":"ITG2","name":"Sardegna","value":77.1769,"binary":0,"link.rca":0,"RD.added":30.3245},{"id":"ITF5","name":"Basilicata","value":90.3758,"binary":0,"link.rca":0,"RD.added":42.3281},{"id":"NL12","name":"Friesland (NL)","value":42.2548,"binary":0,"link.rca":0,"RD.added":8.6325},{"id":"SK04","name":"Východné Slovensko","value":70.5775,"binary":0,"link.rca":0,"RD.added":25.177},{"id":"DEG0","name":"Thüringen","value":95.6004,"binary":0,"link.rca":0,"RD.added":48.6254},{"id":"PL63","name":"Pomorskie","value":55.5454,"binary":0,"link.rca":0,"RD.added":13.662},{"id":"CH02","name":"Espace Mittelland","value":84.3263,"binary":0,"link.rca":0,"RD.added":35.6907},{"id":"UKC1","name":"Tees Valley and Durham","value":43.3547,"binary":0,"link.rca":0,"RD.added":9.6112},{"id":"AT13","name":"Wien","value":81.3016,"binary":0,"link.rca":0,"RD.added":33.2684},{"id":"SE22","name":"Sydsverige","value":85.1512,"binary":0,"link.rca":0,"RD.added":37.9702},{"id":"UKG3","name":"West Midlands","value":63.5197,"binary":0,"link.rca":0,"RD.added":17.9226},{"id":"FI1B","name":"Helsinki-Uusimaa","value":80.4766,"binary":0,"link.rca":0,"RD.added":32.9338},{"id":"ES51","name":"Cataluña","value":73.3272,"binary":0,"link.rca":0,"RD.added":27.6464},{"id":"SE21","name":"Småland med öarna","value":54.9954,"binary":0,"link.rca":0,"RD.added":13.574},{"id":"FR24","name":"Centre","value":43.9047,"binary":0,"link.rca":0,"RD.added":9.7824},{"id":"HU31","name":"Észak-Magyarország","value":60.22,"binary":0,"link.rca":0,"RD.added":16.0345},{"id":"ES12","name":"Principado de Asturias","value":59.945,"binary":0,"link.rca":0,"RD.added":15.8665},{"id":"SK01","name":"Bratislavský kraj","value":72.2273,"binary":0,"link.rca":0,"RD.added":26.9121},{"id":"ITF6","name":"Calabria","value":92.8506,"binary":0,"link.rca":0,"RD.added":44.9679},{"id":"ITF3","name":"Campania","value":50.2291,"binary":0,"link.rca":0,"RD.added":11.5684},{"id":"UKE4","name":"West Yorkshire","value":91.2007,"binary":0,"link.rca":0,"RD.added":43.4998},{"id":"DE24","name":"Oberfranken","value":95.3254,"binary":0,"link.rca":0,"RD.added":48.4979},{"id":"AT33","name":"Tirol","value":78.5518,"binary":0,"link.rca":0,"RD.added":31.8726},{"id":"PL21","name":"Małopolskie","value":60.495,"binary":0,"link.rca":0,"RD.added":16.0493},{"id":"AT22","name":"Steiermark","value":58.2951,"binary":0,"link.rca":0,"RD.added":14.7797},{"id":"ES11","name":"Galicia","value":33.4555,"binary":0,"link.rca":0,"RD.added":5.332},{"id":"DE93","name":"Lüneburg","value":46.3795,"binary":0,"link.rca":0,"RD.added":10.7995},{"id":"NO06","name":"Trøndelag","value":84.0513,"binary":0,"link.rca":0,"RD.added":35.627},{"id":"CY00","name":"Kýpros","value":90.9258,"binary":0,"link.rca":0,"RD.added":43.2785},{"id":"DE94","name":"Weser-Ems","value":32.0807,"binary":0,"link.rca":0,"RD.added":4.0273},{"id":"CH04","name":"Zürich","value":100,"binary":0,"link.rca":0,"RD.added":61.7328},{"id":"UKD1","name":"Cumbria","value":51.0541,"binary":0,"link.rca":0,"RD.added":11.6552},{"id":"DEA3","name":"Münster","value":38.1302,"binary":0,"link.rca":0,"RD.added":7.0385},{"id":"PL52","name":"Opolskie","value":32.9056,"binary":0,"link.rca":0,"RD.added":4.5399},{"id":"CH01","name":"Région lémanique","value":99.1751,"binary":0,"link.rca":0,"RD.added":56.5351},{"id":"FR25","name":"Basse-Normandie","value":85.7012,"binary":0,"link.rca":0,"RD.added":38.5012},{"id":"NL33","name":"Zuid-Holland","value":64.5738,"binary":6,"link.rca":0,"RD.added":18.2855},{"id":"UKC2","name":"Northumberland and Tyne and Wear","value":52.154,"binary":0,"link.rca":0,"RD.added":12.4166},{"id":"DEA1","name":"Düsseldorf","value":35.3804,"binary":0,"link.rca":0,"RD.added":6.1108},{"id":"DE13","name":"Freiburg","value":53.7122,"binary":1,"link.rca":1.16,"RD.added":40.9427},{"id":"FR72","name":"Auvergne","value":31.8057,"binary":0,"link.rca":0,"RD.added":3.7665},{"id":"PT18","name":"Alentejo","value":32.6306,"binary":0,"link.rca":0,"RD.added":4.3523},{"id":"EL65","name":"Peloponnisos","value":48.0293,"binary":0,"link.rca":0,"RD.added":11.0313},{"id":"UKE1","name":"East Yorkshire and Northern Lincolnshire","value":92.3006,"binary":0,"link.rca":0,"RD.added":44.5724},{"id":"DEF0","name":"Schleswig-Holstein","value":83.7764,"binary":1,"link.rca":0,"RD.added":35.5359},{"id":"DEB3","name":"Rheinhessen-Pfalz","value":35.1054,"binary":0,"link.rca":0,"RD.added":6.0471},{"id":"FI1C","name":"Etelä-Suomi","value":52.9789,"binary":0,"link.rca":0,"RD.added":12.9506},{"id":"UKH1","name":"East Anglia","value":90.6508,"binary":0,"link.rca":0,"RD.added":42.3595},{"id":"FR71","name":"Rhône-Alpes","value":34.1888,"binary":1,"link.rca":1.16,"RD.added":22.7391},{"id":"IE02","name":"Southern and Eastern","value":63.6114,"binary":1,"link.rca":1.16,"RD.added":52.8398},{"id":"NL21","name":"Overijssel","value":45.0046,"binary":0,"link.rca":0,"RD.added":10.2392},{"id":"DK01","name":"Hovedstaden","value":59.7617,"binary":1,"link.rca":1.16,"RD.added":46.1676},{"id":"UKD3","name":"Greater Manchester","value":56.9203,"binary":1,"link.rca":0,"RD.added":14.318},{"id":"NL33","name":"Zuid-Holland","value":64.5738,"binary":3,"link.rca":0,"RD.added":18.2855},{"id":"NL31","name":"Utrecht","value":54.308,"binary":4,"link.rca":0,"RD.added":13.2577},{"id":"BE23","name":"Prov. Oost-Vlaanderen","value":44.7296,"binary":0,"link.rca":0,"RD.added":10.0828},{"id":"UKI1","name":"Inner London","value":59.3951,"binary":2,"link.rca":2.33,"RD.added":47.2402},{"id":"FI1D","name":"Pohjois- ja Itä-Suomi","value":91.4757,"binary":0,"link.rca":0,"RD.added":44.0342},{"id":"UKJ4","name":"Kent","value":66.1778,"binary":1,"link.rca":0,"RD.added":19.6892},{"id":"FR81","name":"Languedoc-Roussillon","value":97.5252,"binary":1,"link.rca":0,"RD.added":50.8983},{"id":"NL42","name":"Limburg (NL)","value":45.5545,"binary":0,"link.rca":0,"RD.added":10.5507},{"id":"ES52","name":"Comunidad Valenciana","value":78.8268,"binary":0,"link.rca":0,"RD.added":31.8835},{"id":"SE23","name":"Västsverige","value":49.6792,"binary":1,"link.rca":0,"RD.added":11.4933},{"id":"SE12","name":"Östra Mellansverige","value":59.67,"binary":1,"link.rca":0,"RD.added":15.7888},{"id":"DED2","name":"Dresden","value":63.7947,"binary":1,"link.rca":0,"RD.added":18.0011},{"id":"NL22","name":"Gelderland","value":41.1549,"binary":6,"link.rca":0,"RD.added":8.1425},{"id":"NL22","name":"Gelderland","value":41.1549,"binary":1,"link.rca":0,"RD.added":8.1425},{"id":"UKJ1","name":"Berkshire, Buckinghamshire and Oxfordshire","value":62.2365,"binary":1,"link.rca":1.16,"RD.added":49.8548},{"id":"DE92","name":"Hannover","value":40.055,"binary":1,"link.rca":0,"RD.added":8.0874},{"id":"CH02","name":"Espace Mittelland","value":48.6251,"binary":3,"link.rca":3.49,"RD.added":35.6907},{"id":"NL41","name":"Noord-Brabant","value":65.9487,"binary":5,"link.rca":0.97,"RD.added":59.2877},{"id":"CH01","name":"Région lémanique","value":63.7947,"binary":2,"link.rca":2.33,"RD.added":56.5351},{"id":"UKI1","name":"Inner London","value":60.3116,"binary":1,"link.rca":1.16,"RD.added":47.2402},{"id":"NL32","name":"Noord-Holland","value":54.7663,"binary":3,"link.rca":0,"RD.added":13.5026},{"id":"UKJ2","name":"Surrey, East and West Sussex","value":44.5463,"binary":2,"link.rca":2.33,"RD.added":32.2805},{"id":"NL42","name":"Limburg (NL)","value":45.5545,"binary":1,"link.rca":0,"RD.added":10.5507},{"id":"NL31","name":"Utrecht","value":54.308,"binary":6,"link.rca":0,"RD.added":13.2577},{"id":"DE13","name":"Freiburg","value":88.176,"binary":0,"link.rca":0,"RD.added":40.9427},{"id":"CH04","name":"Zürich","value":65.5362,"binary":1,"link.rca":1.16,"RD.added":61.7328},{"id":"FR71","name":"Rhône-Alpes","value":33.2722,"binary":2,"link.rca":2.33,"RD.added":22.7391},{"id":"CH03","name":"Nordwestschweiz","value":58.6618,"binary":1,"link.rca":1.16,"RD.added":44.9691},{"id":"DE21","name":"Oberbayern","value":29.6975,"binary":2,"link.rca":2.33,"RD.added":18.6341},{"id":"DED4","name":"Chemnitz","value":42.5298,"binary":2,"link.rca":0,"RD.added":9.0724},{"id":"BE21","name":"Prov. Antwerpen","value":35.2887,"binary":1,"link.rca":1.16,"RD.added":23.7792},{"id":"EL30","name":"Attiki","value":54.5371,"binary":1,"link.rca":0,"RD.added":13.5018},{"id":"BE22","name":"Prov. Limburg (BE)","value":74.7021,"binary":2,"link.rca":0,"RD.added":28.5379},{"id":"DEA1","name":"Düsseldorf","value":0,"binary":2,"link.rca":2.33,"RD.added":6.1108},{"id":"FR52","name":"Bretagne","value":60.0367,"binary":1,"link.rca":1.16,"RD.added":46.3949},{"id":"FR10","name":"Île de France","value":28.7809,"binary":2,"link.rca":1.16,"RD.added":17.737},{"id":"UKI2","name":"Outer London","value":63.8863,"binary":1,"link.rca":1.16,"RD.added":54.1768}]
